configs/api.py
configs/config.py
configs/sample.conf
configs/section.py
configs/__init__.py
configs-3.0.3.dist-info/DESCRIPTION.rst
configs-3.0.3.dist-info/METADATA
configs-3.0.3.dist-info/metadata.json
configs-3.0.3.dist-info/RECORD
configs-3.0.3.dist-info/top_level.txt
configs-3.0.3.dist-info/WHEEL
