Metadata-Version: 1.1
Name: configs
Version: 3.0.3
Summary: Configuration for humans
Home-page: https://bitbucket.org/moigagoo/configs
Author: Konstantin Molchanov
Author-email: moigagoo@live.com
License: MIT
Platform: UNKNOWN
Classifier: Development Status :: 5 - Production/Stable
Classifier: Intended Audience :: Developers
Classifier: Natural Language :: English
Classifier: Programming Language :: Python
Classifier: Programming Language :: Python :: 3
